jayhawk/__init__.py
jayhawk/dispatch.py
jayhawk-1.1.1.dist-info/LICENSE
jayhawk-1.1.1.dist-info/WHEEL
jayhawk-1.1.1.dist-info/METADATA
jayhawk-1.1.1.dist-info/RECORD
